README.txt
setup.py
collective/__init__.py
collective.bloggingmaps.egg-info/PKG-INFO
collective.bloggingmaps.egg-info/SOURCES.txt
collective.bloggingmaps.egg-info/dependency_links.txt
collective.bloggingmaps.egg-info/entry_points.txt
collective.bloggingmaps.egg-info/namespace_packages.txt
collective.bloggingmaps.egg-info/not-zip-safe
collective.bloggingmaps.egg-info/paster_plugins.txt
collective.bloggingmaps.egg-info/requires.txt
collective.bloggingmaps.egg-info/top_level.txt
collective/bloggingmaps/README.txt
collective/bloggingmaps/__init__.py
collective/bloggingmaps/adapter.py
collective/bloggingmaps/configure.zcml
collective/bloggingmaps/extenders.py
collective/bloggingmaps/interfaces.py
collective/bloggingmaps/tests.py
collective/bloggingmaps/update_i18n.sh
collective/bloggingmaps/locales/collective.bloggingmaps.pot
collective/bloggingmaps/locales/cs/LC_MESSAGES/collective.bloggingmaps.po
collective/bloggingmaps/locales/en/LC_MESSAGES/collective.bloggingmaps.po
collective/bloggingmaps/locales/nl/LC_MESSAGES/collective.bloggingmaps.po
collective/bloggingmaps/profiles/default/browserlayer.xml
collective/bloggingmaps/profiles/default/metadata.xml
docs/HISTORY.txt
docs/INSTALL.txt
docs/LICENSE.GPL
docs/LICENSE.txt