Metadata-Version: 1.0
Name: collective.bloggingmaps
Version: 1.0b2
Summary: An extension for Plone which adds google maps support for collective.blogging package.
Home-page: http://plone.org/products/collective.bloggingmaps
Author: Lukas Zdych
Author-email: lukas.zdych@gmail.com
License: GPL
Keywords: plone blogging maps
Platform: UNKNOWN
Classifier: Framework :: Plone
Classifier: Programming Language :: Python
